Metadata-Version: 2.1
Name: custom-django-allauth
Version: 0.45.0
Summary: Integrated set of Django applications addressing authentication, registration, account management as well as 3rd party (social) account authentication.
Home-page: https://github.com/Venus713/custom-django-allauth
Author: venus713
Author-email: userstar713@gmail.com
License: UNKNOWN
Keywords: django auth account social openid twitter facebook oauth registration
Platform: UNKNOWN
Classifier: Development Status :: 4 - Beta
Classifier: Intended Audience :: Developers
Classifier: Topic :: Software Development :: Libraries :: Python Modules
Classifier: Environment :: Web Environment
Classifier: Topic :: Internet
Classifier: License :: OSI Approved :: MIT License
Classifier: Operating System :: OS Independent
Classifier: Programming Language :: Python
Classifier: Programming Language :: Python :: 3
Classifier: Programming Language :: Python :: 3.5
Classifier: Programming Language :: Python :: 3.6
Classifier: Programming Language :: Python :: 3.7
Classifier: Programming Language :: Python :: 3.8
Classifier: Programming Language :: Python :: 3.9
Classifier: Framework :: Django
Classifier: Framework :: Django :: 2.0
Classifier: Framework :: Django :: 2.1
Classifier: Framework :: Django :: 2.2
Classifier: Framework :: Django :: 3.0
License-File: LICENSE
License-File: AUTHORS
Requires-Dist: Django (>=2.0)
Requires-Dist: python3-openid (>=3.0.8)
Requires-Dist: requests-oauthlib (>=0.3.0)
Requires-Dist: requests
Requires-Dist: pyjwt[crypto] (>=1.7)
